README
setup.py
python_redis_logger.egg-info/PKG-INFO
python_redis_logger.egg-info/SOURCES.txt
python_redis_logger.egg-info/dependency_links.txt
python_redis_logger.egg-info/requires.txt
python_redis_logger.egg-info/top_level.txt
redis_logger/__init__.py
redis_logger/redis_logger.py