Metadata-Version: 1.0
Name: python-redis-logger
Version: 0.1.3
Summary: Persistent redis logger for python
Home-page: https://github.com/teodor-pripoae/python-redis-logger
Author: Teodor Pripoae
Author-email: toni@netbaiji.com
License: UNKNOWN
Platform: UNKNOWN
